canny/__init__.py
canny/async_client.py
canny/client.py
canny/config.py
canny/exceptions.py
canny/http.py
canny/pagination.py
canny/py.typed
canny/webhooks.py
canny/models/__init__.py
canny/models/base.py
canny/models/boards.py
canny/models/categories.py
canny/models/comments.py
canny/models/companies.py
canny/models/entries.py
canny/models/groups.py
canny/models/posts.py
canny/models/roadmaps.py
canny/models/status_changes.py
canny/models/tags.py
canny/models/users.py
canny/models/votes.py
canny/models/webhooks.py
canny/resources/__init__.py
canny/resources/base.py
canny/resources/boards.py
canny/resources/categories.py
canny/resources/comments.py
canny/resources/companies.py
canny/resources/entries.py
canny/resources/groups.py
canny/resources/posts.py
canny/resources/status_changes.py
canny/resources/tags.py
canny/resources/users.py
canny/resources/votes.py
canny_sdk-0.1.0a1.dist-info/METADATA
canny_sdk-0.1.0a1.dist-info/WHEEL
canny_sdk-0.1.0a1.dist-info/licenses/LICENSE
canny_sdk-0.1.0a1.dist-info/RECORD
