Metadata-Version: 2.4
Name: canny-sdk
Version: 0.1.0a1
Summary: Unofficial Python SDK for Canny API
License-Expression: MIT
License-File: LICENSE
Keywords: api,canny,feedback,product-management,sdk
Classifier: Development Status :: 3 - Alpha
Classifier: Intended Audience :: Developers
Classifier: License :: OSI Approved :: MIT License
Classifier: Programming Language :: Python :: 3
Classifier: Programming Language :: Python :: 3.9
Classifier: Programming Language :: Python :: 3.10
Classifier: Programming Language :: Python :: 3.11
Classifier: Programming Language :: Python :: 3.12
Classifier: Programming Language :: Python :: 3.13
Classifier: Typing :: Typed
Requires-Python: >=3.9
Requires-Dist: httpx>=0.25.0
Requires-Dist: pydantic>=2.0.0
Provides-Extra: dev
Requires-Dist: mypy>=1.0; extra == 'dev'
Requires-Dist: pytest-asyncio>=0.21; extra == 'dev'
Requires-Dist: pytest-cov>=4.0; extra == 'dev'
Requires-Dist: pytest>=7.0; extra == 'dev'
Requires-Dist: respx>=0.20; extra == 'dev'
Requires-Dist: ruff>=0.1.0; extra == 'dev'
